LICENSE
README.md
setup.py
pynaja/__init__.py
pynaja.egg-info/PKG-INFO
pynaja.egg-info/SOURCES.txt
pynaja.egg-info/dependency_links.txt
pynaja.egg-info/requires.txt
pynaja.egg-info/top_level.txt
pynaja/cache/__init__.py
pynaja/cache/base.py
pynaja/cache/redis.py
pynaja/common/__init__.py
pynaja/common/async_base.py
pynaja/common/base.py
pynaja/common/error.py
pynaja/common/metaclass.py
pynaja/common/process.py
pynaja/common/struct.py
pynaja/common/task.py
pynaja/database/__init__.py
pynaja/database/mongo.py
pynaja/database/mysql.py
pynaja/enum/__init__.py
pynaja/enum/base_enum.py
pynaja/event/__init__.py
pynaja/event/async_event.py
pynaja/event/event.py
pynaja/frame/__init__.py
pynaja/frame/logging.py
pynaja/frame/fastapi/__init__.py
pynaja/frame/fastapi/base.py
pynaja/frame/fastapi/form.py
pynaja/frame/fastapi/response.py
pynaja/net/__init__.py
pynaja/net/http.py
pynaja/scaffold/__init__.py
pynaja/scaffold/fastapi_example_project/__init__.py
pynaja/scaffold/fastapi_example_project/activate.py
pynaja/scaffold/fastapi_example_project/err_handler.py
pynaja/scaffold/fastapi_example_project/main.py
pynaja/scaffold/fastapi_example_project/manage.py
pynaja/scaffold/fastapi_example_project/router.py
pynaja/scaffold/fastapi_example_project/abc_base/__init__.py
pynaja/scaffold/fastapi_example_project/abc_base/model/__init__.py
pynaja/scaffold/fastapi_example_project/abc_base/model/base_model.py
pynaja/scaffold/fastapi_example_project/abc_base/service/__init__.py
pynaja/scaffold/fastapi_example_project/abc_base/service/base_service.py
pynaja/scaffold/fastapi_example_project/abc_base/view/__init__.py
pynaja/scaffold/fastapi_example_project/abc_base/view/base_view.py
pynaja/scaffold/fastapi_example_project/apps/__init__.py
pynaja/scaffold/fastapi_example_project/apps/example_app/__init__.py
pynaja/scaffold/fastapi_example_project/apps/example_app/external_view.py
pynaja/scaffold/fastapi_example_project/apps/example_app/internal_view.py
pynaja/scaffold/fastapi_example_project/apps/example_app/model.py
pynaja/scaffold/fastapi_example_project/apps/example_app/schemas.py
