Metadata-Version: 2.1
Name: pynaja
Version: 1.0.3
Summary: Async Suite For Python
Home-page: https://github.com/xiaoxiamiya/naja.git
Author: xiami
Author-email: gaohlsilence@163.com
License: Apache License Version 2.0
Platform: all
Classifier: Programming Language :: Python :: 3.8
Classifier: License :: OSI Approved :: Apache Software License
Classifier: Operating System :: POSIX :: Linux
Requires-Python: >= 3.8
License-File: LICENSE
